slick/__init__.py
slick/cli.py
slick/py.typed
slick_ai-0.1.0.dist-info/LICENSE
slick_ai-0.1.0.dist-info/METADATA
slick_ai-0.1.0.dist-info/WHEEL
slick_ai-0.1.0.dist-info/entry_points.txt
slick_ai-0.1.0.dist-info/RECORD
