Metadata-Version: 2.1
Name: slick-ai
Version: 0.1.0
Summary: Slick: simple agentic AI.
License: MIT
Author: Stuart Farmer
Author-email: stuart@lamden.io
Requires-Python: >=3.9,<4.0
Classifier: License :: OSI Approved :: MIT License
Classifier: Programming Language :: Python :: 3
Classifier: Programming Language :: Python :: 3.9
Classifier: Programming Language :: Python :: 3.10
Classifier: Programming Language :: Python :: 3.11
Classifier: Programming Language :: Python :: 3.12
